light_cnns/__init__.py
light_cnns/AdderNet/__init__.py
light_cnns/AdderNet/addernet.py
light_cnns/AdderNet/resnet20.py
light_cnns/AdderNet/resnet50.py
light_cnns/Attention/CANet.py
light_cnns/Attention/TripletNet.py
light_cnns/Attention/__init__.py
light_cnns/Attention/ecanet.py
light_cnns/Attention/resnest.py
light_cnns/Attention/sanet.py
light_cnns/ESPNet/__init__.py
light_cnns/ESPNet/espnetv1.py
light_cnns/ESPNet/espnetv2.py
light_cnns/ESPNet/utils.py
light_cnns/GhostNet/__init__.py
light_cnns/GhostNet/ghostnet.py
light_cnns/HRNet/__init__.py
light_cnns/HRNet/cls_hrnet.py
light_cnns/HRNet/det_hrnet.py
light_cnns/HRNet/hrformer.py
light_cnns/HRNet/lite_hrnet.py
light_cnns/Inception/Xception.py
light_cnns/Inception/__init__.py
light_cnns/Inception/inception_nas.py
light_cnns/Inception/inception_v1.py
light_cnns/Inception/inception_v2.py
light_cnns/Inception/inception_v3.py
light_cnns/Inception/inception_v4.py
light_cnns/Inception/pattern_zoo/__init__.py
light_cnns/MobileNet/__init__.py
light_cnns/MobileNet/mobilenetv1.py
light_cnns/MobileNet/mobilenetv2.py
light_cnns/MobileNet/mobilenetv3.py
light_cnns/MobileNet/mobilenext.py
light_cnns/ResNet_D/__init__.py
light_cnns/ResNet_D/resnet_d.py
light_cnns/ShuffleNet/__init__.py
light_cnns/ShuffleNet/blocks/__init__.py
light_cnns/ShuffleNet/blocks/one_shot_NAS.py
light_cnns/ShuffleNet/blocks/shuffle_v2_block.py
light_cnns/ShuffleNet/blocks/shufflev1_block.py
light_cnns/ShuffleNet/models/OneShot_NAS.py
light_cnns/ShuffleNet/models/ShuffleNetV2.py
light_cnns/ShuffleNet/models/ShuffleNetv1.py
light_cnns/ShuffleNet/models/__init__.py
light_cnns/Transformer/__init__.py
light_cnns/Transformer/levit.py
light_cnns/Transformer/mobile_vit.py
light_cnns/mobile_real_time_network/__init__.py
light_cnns/mobile_real_time_network/lcnet.py
light_cnns/mobile_real_time_network/parnet.py
light_cnns/mobile_real_time_network/peleenet.py
light_cnns-0.4.2.dist-info/LICENSE
light_cnns-0.4.2.dist-info/METADATA
light_cnns-0.4.2.dist-info/WHEEL
light_cnns-0.4.2.dist-info/top_level.txt
light_cnns-0.4.2.dist-info/RECORD
